brewflasher_cli/__init__.py
brewflasher_cli/brewflasher_cli_edition.py
brewflasher_cli/brewflasher_com_integration.py
brewflasher_cli/fhash.py
brewflasher_cli/serial_integration.py
brewflasher_cli-0.1.1.dist-info/LICENSE
brewflasher_cli-0.1.1.dist-info/METADATA
brewflasher_cli-0.1.1.dist-info/WHEEL
brewflasher_cli-0.1.1.dist-info/entry_points.txt
brewflasher_cli-0.1.1.dist-info/top_level.txt
brewflasher_cli-0.1.1.dist-info/RECORD
