Metadata-Version: 2.1
Name: brewflasher-cli
Version: 0.1.1
Summary: BrewFlasher Command Line Tool
Author-email: John Beeler <author@example.com>
Project-URL: Homepage, https://github.com/thorrak/brewflasher_cli
Project-URL: Bug Tracker, https://github.com/thorrak/brewflasher_cli/issues
Classifier: Programming Language :: Python :: 3
Classifier: License :: OSI Approved :: MIT License
Classifier: Operating System :: OS Independent
Requires-Python: >=3.6
License-File: LICENSE
Requires-Dist: requests >=2.31.0
Requires-Dist: pyserial >=3.5
Requires-Dist: click >=8.1.6
Requires-Dist: esptool >=4.6.2
